micromet/__init__.py
micromet/reader.py
micromet/station_data_pull.py
micromet/station_info.py
micromet/utils.py
micromet/data/Flux_variables.csv
micromet/data/US-CdM.ini
micromet/data/US-UTB.ini
micromet/data/US-UTD.ini
micromet/data/US-UTE.ini
micromet/data/US-UTG.ini
micromet/data/US-UTJ.ini
micromet/data/US-UTM.ini
micromet/data/US-UTN.ini
micromet/data/US-UTP.ini
micromet/data/US-UTV.ini
micromet/data/US-UTW.ini
micromet/data/extreme_values.csv
micromet/format/__init__.py
micromet/format/add_header_from_peer.py
micromet/format/compare.py
micromet/format/file_compile.py
micromet/format/headers.py
micromet/format/reformatter.py
micromet/format/reformatter_vars.py
micromet/format/transformers.py
micromet/qaqc/__init__.py
micromet/qaqc/netrad_limits.py
micromet/qaqc/variable_limits.py
micromet/report/__init__.py
micromet/report/gap_summary.py
micromet/report/graphs.py
micromet/report/tools.py
micromet/report/validate.py
micromet-0.3.1.dist-info/licenses/LICENSE
micromet-0.3.1.dist-info/METADATA
micromet-0.3.1.dist-info/WHEEL
micromet-0.3.1.dist-info/top_level.txt
micromet-0.3.1.dist-info/RECORD
