Metadata-Version: 2.4
Name: micromet
Version: 0.3.1
Summary: A comprehensive Python package for micrometeorological data analysis
Author-email: Paul Inkenbrandt <paulinkenbrandt@utah.gov>, Kathryn Ladig <kladig@utah.gov>, Diane Menuz <dmenuz@utah.gov>
License: GNU General Public License v3.0
Project-URL: Homepage, https://github.com/inkenbrandt/micromet
Project-URL: Documentation, https://micromet.readthedocs.io/en/stable/
Requires-Python: >=3.11
License-File: LICENSE
Requires-Dist: numpy>=1.20
Requires-Dist: pandas>=1.3
Requires-Dist: scipy>=1.7
Requires-Dist: matplotlib>=3.4
Requires-Dist: plotly>=5.0
Requires-Dist: sqlalchemy>=1.4
Requires-Dist: pyyaml>=5.4
Requires-Dist: requests>=2.25
Requires-Dist: pytz>=2021.1
Provides-Extra: docs
Requires-Dist: sphinx>=4.0; extra == "docs"
Requires-Dist: sphinx-rtd-theme>=1.0; extra == "docs"
Requires-Dist: sphinx-copybutton>=0.5; extra == "docs"
Requires-Dist: sphinx-autodoc-typehints>=1.12; extra == "docs"
Requires-Dist: myst-parser>=0.15; extra == "docs"
Provides-Extra: test
Requires-Dist: python>=3.11; extra == "test"
Requires-Dist: pytest>=6.0; extra == "test"
Requires-Dist: pytest-cov>=2.0; extra == "test"
Dynamic: license-file
